dspace_stats_collector/__init__.py
dspace_stats_collector/collector.py
dspace_stats_collector/configcontext.py
dspace_stats_collector/configure.py
dspace_stats_collector/counterfilter.py
dspace_stats_collector/croninstaller.py
dspace_stats_collector/dspacedb.py
dspace_stats_collector/dspacedb4.py
dspace_stats_collector/dspacedb5.py
dspace_stats_collector/dspacedb5cris.py
dspace_stats_collector/dspacedb5oracle.py
dspace_stats_collector/dspacedb6.py
dspace_stats_collector/dspacedb6oracle.py
dspace_stats_collector/dspacedb7.py
dspace_stats_collector/dspacefilter.py
dspace_stats_collector/elasticoutput.py
dspace_stats_collector/eventpipeline.py
dspace_stats_collector/export.py
dspace_stats_collector/fileoutput.py
dspace_stats_collector/matomooutput.py
dspace_stats_collector/sessionfilter.py
dspace_stats_collector/solrinput.py
dspace_stats_collector/test.py
dspace_stats_collector-0.7.8.dist-info/AUTHORS.rst
dspace_stats_collector-0.7.8.dist-info/LICENSE
dspace_stats_collector-0.7.8.dist-info/METADATA
dspace_stats_collector-0.7.8.dist-info/WHEEL
dspace_stats_collector-0.7.8.dist-info/entry_points.txt
dspace_stats_collector-0.7.8.dist-info/top_level.txt
dspace_stats_collector-0.7.8.dist-info/RECORD
