Metadata-Version: 2.1
Name: dspace-stats-collector
Version: 0.7.8
Summary: A python library for sending usage stats events from Dspace to Matomo
Home-page: https://github.com/lareferencia/dspace-stats-collector
Author: LA Referencia
Author-email: soporte@lareferencia.redclara.net
License: GNU General Public License v3
Keywords: dspace_stats_collector
Classifier: License :: OSI Approved :: GNU General Public License v3 (GPLv3)
Classifier: Natural Language :: English
Classifier: Programming Language :: Python :: 3.7
License-File: LICENSE
License-File: AUTHORS.rst
